azureml/__init__.py
azureml/training/__init__.py
azureml/training/tabular/__init__.py
azureml/training/tabular/_types.py
azureml/training/tabular/_version.py
azureml/training/tabular/py.typed
azureml/training/tabular/_constants/__init__.py
azureml/training/tabular/_diagnostics/__init__.py
azureml/training/tabular/_diagnostics/azureml_error.py
azureml/training/tabular/_diagnostics/contract.py
azureml/training/tabular/_diagnostics/debug_logging.py
azureml/training/tabular/_diagnostics/error_definitions.py
azureml/training/tabular/_diagnostics/error_strings.py
azureml/training/tabular/_diagnostics/errors.py
azureml/training/tabular/_diagnostics/logging_utilities.py
azureml/training/tabular/_diagnostics/reference_codes.py
azureml/training/tabular/_diagnostics/validation.py
azureml/training/tabular/featurization/__init__.py
azureml/training/tabular/featurization/_azureml_transformer.py
azureml/training/tabular/featurization/_engineered_feature_names.py
azureml/training/tabular/featurization/_featurization_config.py
azureml/training/tabular/featurization/_featurization_info_provider.py
azureml/training/tabular/featurization/_memory_utilities.py
azureml/training/tabular/featurization/_operator_names.py
azureml/training/tabular/featurization/_raw_feature_stats.py
azureml/training/tabular/featurization/_supported_transformers.py
azureml/training/tabular/featurization/_transformer_exceptions.py
azureml/training/tabular/featurization/utilities.py
azureml/training/tabular/featurization/categorical/__init__.py
azureml/training/tabular/featurization/categorical/cat_imputer.py
azureml/training/tabular/featurization/categorical/hashonehotvectorizer_transformer.py
azureml/training/tabular/featurization/categorical/labelencoder_transformer.py
azureml/training/tabular/featurization/categorical/onehotencoder_transformer.py
azureml/training/tabular/featurization/data/__init__.py
azureml/training/tabular/featurization/data/abstract_wordembeddings_provider.py
azureml_training_tabular-1.60.0.dist-info/licenses/LICENSE.txt
azureml_training_tabular-1.60.0.dist-info/METADATA
azureml_training_tabular-1.60.0.dist-info/WHEEL
azureml_training_tabular-1.60.0.dist-info/top_level.txt
azureml_training_tabular-1.60.0.dist-info/RECORD
